{
  "version": 2,
  "extractor": "pdffigures2",
  "figures": [
    {
      "url": "assets/figures/arxiv/2603.24275v1/fig-001.webp",
      "caption": "Figure 3. Visualization of image-text representation matrix C.",
      "page": 6,
      "index": 1,
      "width": 483,
      "height": 285
    },
    {
      "url": "assets/figures/arxiv/2603.24275v1/fig-002.webp",
      "caption": "Table 5. A summary of benchmark datasets used for evaluation.",
      "page": 11,
      "index": 2,
      "width": 541,
      "height": 240
    },
    {
      "url": "assets/figures/arxiv/2603.24275v1/fig-003.webp",
      "caption": "Figure 1. (a) Analysis of the phenomena in the first step of existing LAICs and our method on the ImageNet-10 dataset. (i) Jointly PCA results shows text features of noun from candidate set exhibit a more compact distribution, which are closed to each other compared to image features. (ii) Due to the phenomenon in (i), the similarity of text features across different samples are overall highly similar, leading to weak inter-class discriminability. (iii) Rows of our learned image-text representation matrix performs as new representation, showing better inter-class discriminability with in-class consistency retained. (b) Classification scores of three images (from DTD dataset) with respect to different semantic centers obtained by different methods. Zero-shot CLIP relies on semantic centers using ground-truth class names, which may not always capture accurate semantics (e.g, an image of motorboat is incorrectly assigned to “Surfing”. Our learned semantic center can be even better than class names, showing stronger discriminability.",
      "page": 2,
      "index": 3,
      "width": 1006,
      "height": 427
    },
    {
      "url": "assets/figures/arxiv/2603.24275v1/fig-004.webp",
      "caption": "Table 1. Clustering performance (in percent %) across four widely used datasets. ZS-CLIP means zero-shot CLIP.",
      "page": 7,
      "index": 4,
      "width": 989,
      "height": 501
    },
    {
      "url": "assets/figures/arxiv/2603.24275v1/fig-005.webp",
      "caption": "Table 2. Clustering performance (in percent %) across four datasets with larger cluster numbers.",
      "page": 7,
      "index": 5,
      "width": 989,
      "height": 254
    },
    {
      "url": "assets/figures/arxiv/2603.24275v1/fig-006.webp",
      "caption": "Figure 8. Clustering performances and percent of selected samples to total samples with different k̂ on CIFAR-10 and DTD.",
      "page": 13,
      "index": 6,
      "width": 1000,
      "height": 239
    },
    {
      "url": "assets/figures/arxiv/2603.24275v1/fig-007.webp",
      "caption": "Figure 4. K-means performances comparisons on our method (Ours (no-train)) and two different baseline methods (CLIP K-means and TAC (no-train))across four datasets.",
      "page": 8,
      "index": 7,
      "width": 979,
      "height": 232
    },
    {
      "url": "assets/figures/arxiv/2603.24275v1/fig-008.webp",
      "caption": "Figure 2. Accuracy of each sample and its k̂-nn (k̂ = 10) belonging to the same ground-truth class on different space. We compare the results by computing similarity on images features from CLIP and rows of C, showing our image-text representation matrix has better neighbor consistency.",
      "page": 4,
      "index": 8,
      "width": 427,
      "height": 328
    },
    {
      "url": "assets/figures/arxiv/2603.24275v1/fig-009.webp",
      "caption": "Figure 6. Clustering performances with different θ on CIFAR-10 and DTD.",
      "page": 12,
      "index": 9,
      "width": 796,
      "height": 258
    },
    {
      "url": "assets/figures/arxiv/2603.24275v1/fig-010.webp",
      "caption": "Figure 7. Clustering performances with different γ on CIFAR-10 and DTD.",
      "page": 12,
      "index": 10,
      "width": 795,
      "height": 260
    }
  ]
}